{
    "line_info": "ул.”11 Октомври”, ул.”ВОЈВОДА ВАСИЛ АЏИЛАРСКИ”, ул. “ Стив Наумов” ,бул”К.Мисирков”, Бул.”Александар Македонски” и ОБРАТНО", 
    "to": "Железара", 
    "times_to": [
        "5:15", 
        "5:50", 
        "6:20", 
        "6:35", 
        "6:51", 
        "7:07", 
        "7:26", 
        "7:40", 
        "7:55", 
        "8:10", 
        "8:32", 
        "8:53", 
        "9:14", 
        "9:36", 
        "9:57", 
        "10:18", 
        "10:40", 
        "11:01", 
        "11:22", 
        "11:44", 
        "12:05", 
        "12:26", 
        "12:48", 
        "13:20", 
        "13:36", 
        "13:52", 
        "14:08", 
        "14:24", 
        "14:40", 
        "15:00", 
        "15:15", 
        "15:28", 
        "15:50", 
        "16:10", 
        "16:32", 
        "17:04", 
        "17:36", 
        "18:08", 
        "18:40", 
        "19:12", 
        "19:44", 
        "20:16", 
        "20:50", 
        "21:20", 
        "22:30"
    ], 
    "from": "Пржино", 
    "times_from": [
        "5:15", 
        "5:50", 
        "6:20", 
        "6:35", 
        "6:51", 
        "7:07", 
        "7:23", 
        "7:39", 
        "8:00", 
        "8:21", 
        "8:42", 
        "9:04", 
        "9:25", 
        "9:46", 
        "10:08", 
        "10:29", 
        "10:50", 
        "11:12", 
        "11:33", 
        "11:54", 
        "12:16", 
        "12:37", 
        "12:58", 
        "13:20", 
        "13:36", 
        "13:52", 
        "14:08", 
        "14:24", 
        "14:45", 
        "14:56", 
        "15:12", 
        "15:30", 
        "15:47", 
        "16:00", 
        "16:22", 
        "16:42", 
        "17:04", 
        "17:36", 
        "18:08", 
        "18:40", 
        "19:12", 
        "19:44", 
        "20:16", 
        "20:48", 
        "21:25", 
        "22:00", 
        "23:00"
    ]
}