{
    "line_info": "", 
    "to": "Никиштани", 
    "times_to": [
        "5:25", 
        "5:50", 
        "6:22", 
        "6:47", 
        "11:56", 
        "12:45", 
        "13:43", 
        "14:30", 
        "15:10", 
        "16:20 до Волково", 
        "17:12 до Волково", 
        "18:45 до Ѓ.П.", 
        "5:10 од Кучково до Волково", 
        "6:30 од Кучково до Волково", 
        "8:10 од Кучково до Волково", 
        "12:25 од Кучково до Волково", 
        "15:30 од Кучково до Волково", 
        "17:15 од Кучково до Волково", 
        "19:35 од Кучково до Волково", 
        "22:50 од Кучково до Волково", 
        "4:50 од Никиштани до Волково", 
        "8:35 од Никиштани до Волково", 
        "10:30 од Никиштани до Волково", 
        "11:00 од Никиштани до Волково", 
        "12:45 од Никиштани до Волково", 
        "15:50 од Никиштани до Волково", 
        "19:10 од Никиштани до Волково", 
        "21:20 од Никиштани до Волково", 
        "22:30 од Никиштани до Волково", 
        "23:15 од Никиштани до Волково"
    ], 
    "from": "Транспортен центар", 
    "times_from": [
        "6:30", 
        "11:03", 
        "12:50", 
        "13:40", 
        "14:20", 
        "15:30", 
        "16:22", 
        "19:30",
        "5:00 од Волково до Кучково", 
        "6:20 од Волково до Кучково", 
        "8:00 од Волково до Кучково", 
        "12:10 од Волково до Кучково", 
        "15:15 од Волково до Кучково", 
        "17:00 од Волково до Кучково", 
        "19:25 од Волково до Кучково", 
        "22:40 од Волково до Кучково", 
        "5:40 од Волково до Никиштани", 
        "8:25 од Волково до Никиштани", 
        "10:20 од Волково до Никиштани", 
        "10:50 од Волково до Никиштани", 
        "12:35 од Волково до Никиштани", 
        "15:40 од Волково до Никиштани", 
        "19:00 од Волково до Никиштани", 
        "21:10 од Волково до Никиштани", 
        "22:20 од Волково до Никиштани", 
        "23:05 од Волково до Никиштани"
    ]
}