{
    "line_info": "", 
    "to": "Визбегово:", 
    "times_to": [
        "6:00", 
        "7:00", 
        "8:00", 
        "9:10", 
        "10:20", 
        "11:30", 
        "12:50", 
        "14:00", 
        "15:10", 
        "16:20", 
        "17:30", 
        "18:40", 
        "19:50", 
        "21:05", 
        "22:10 до партизанска"
    ], 
    "from": "Транспортен центар", 
    "times_from": [
        "6:30", 
        "7:30", 
        "8:35", 
        "9:45", 
        "10:55", 
        "12:10", 
        "13:25", 
        "14:35", 
        "15:45", 
        "16:55", 
        "18:05", 
        "19:15", 
        "20:20", 
        "21:40"
    ]
}